.coveragerc
.travis.yml
CHANGES.rst
LICENSE.txt
MANIFEST.in
README.rst
development.ini
i18n.sh
requirements.txt
rtd.txt
setup.cfg
setup.py
kotti_socialbuttons/__init__.py
kotti_socialbuttons/fanstatic.py
kotti_socialbuttons/populate.py
kotti_socialbuttons.egg-info/PKG-INFO
kotti_socialbuttons.egg-info/SOURCES.txt
kotti_socialbuttons.egg-info/dependency_links.txt
kotti_socialbuttons.egg-info/entry_points.txt
kotti_socialbuttons.egg-info/not-zip-safe
kotti_socialbuttons.egg-info/requires.txt
kotti_socialbuttons.egg-info/top_level.txt
kotti_socialbuttons/locale/.gitkeep
kotti_socialbuttons/locale/kotti_socialbuttons.pot
kotti_socialbuttons/locale/de/LC_MESSAGES/kotti_socialbuttons.mo
kotti_socialbuttons/locale/de/LC_MESSAGES/kotti_socialbuttons.po
kotti_socialbuttons/locale/en/LC_MESSAGES/kotti_socialbuttons.mo
kotti_socialbuttons/locale/en/LC_MESSAGES/kotti_socialbuttons.po
kotti_socialbuttons/static/socialshareprivacy/jquery.socialshareprivacy.de.js
kotti_socialbuttons/static/socialshareprivacy/jquery.socialshareprivacy.de.min.js
kotti_socialbuttons/static/socialshareprivacy/jquery.socialshareprivacy.en.js
kotti_socialbuttons/static/socialshareprivacy/jquery.socialshareprivacy.en.min.js
kotti_socialbuttons/static/socialshareprivacy/jquery.socialshareprivacy.js
kotti_socialbuttons/static/socialshareprivacy/jquery.socialshareprivacy.min.js
kotti_socialbuttons/static/socialshareprivacy/socialshareprivacy.css
kotti_socialbuttons/static/socialshareprivacy/socialshareprivacy.min.css
kotti_socialbuttons/static/socialshareprivacy/images/ssp_sprite.png
kotti_socialbuttons/tests/test_view.py
kotti_socialbuttons/tests/__pycache__/test_view.cpython-27-PYTEST.pyc
kotti_socialbuttons/views/__init__.py
kotti_socialbuttons/views/__init__.pyc
kotti_socialbuttons/views/view.py
kotti_socialbuttons/views/view.pyc